MANIFEST.in
README.rst
setup.py
gohttp/__init__.py
gohttp/__main__.py
gohttp/_gohttplib.py
gohttp/build_gohttplib.py
gohttp/libgohttp.so
gohttp.egg-info/PKG-INFO
gohttp.egg-info/SOURCES.txt
gohttp.egg-info/dependency_links.txt
gohttp.egg-info/requires.txt
gohttp.egg-info/top_level.txt