Metadata-Version: 1.1
Name: gohttp
Version: 0.3.1
Summary: Bindings for gohttplib, exposing Go's http.Server
Home-page: https://github.com/shazow/gohttplib
Author: Andrey Petrov
Author-email: andrey.petrov@shazow.net
License: UNKNOWN
Platform: UNKNOWN
Classifier: Programming Language :: Python :: 2
Classifier: Programming Language :: Python :: 3
Classifier: License :: OSI Approved :: MIT License
